<?xml version="1.0" encoding="utf-8" ?><dwsync><file name="index.html" server="linux242.unoeuro.com" local="3621504477" remote="3621506700" Dst="-1" /><file name=".gitattributes" server="linux242.unoeuro.com" local="3621221614" remote="3621506700" Dst="-1" /><file name="index.html" server="linux242.unoeuro.com//" local="3621504477" remote="3622625340" Dst="-1" /><file name=".gitattributes" server="linux242.unoeuro.com//" local="3621221614" remote="3622625340" Dst="-1" /><file name="index.html" server="linux242.unoeuro.com//public_html/" local="3621504477" remote="3622625580" Dst="-1" /><file name=".gitattributes" server="linux242.unoeuro.com//public_html/" local="3621221614" remote="3622625580" Dst="-1" /><file name="index.html" server="linux242.unoeuro.com/public_html/" local="3622625580" remote="3622625580" Dst="-1" /><file name=".gitattributes" server="linux242.unoeuro.com/public_html/" local="3622625580" remote="3622625580" Dst="-1" /></dwsync>